curva/__init__.py
curva/aes.py
curva/key.py
curva/test.py
curva-1.1.dist-info/LICENSE
curva-1.1.dist-info/METADATA
curva-1.1.dist-info/WHEEL
curva-1.1.dist-info/top_level.txt
curva-1.1.dist-info/RECORD
