Metadata-Version: 2.1
Name: curva
Version: 1.1
Summary: Simple library for ECIES with AES and HKDF.
Home-page: http://github.com/origamizyt/curva
Author: origamizyt
Author-email: zhaoyitong18@163.com
License: UNKNOWN
Platform: UNKNOWN
Classifier: Programming Language :: Python :: 3
Classifier: License :: OSI Approved :: MIT License
Classifier: Operating System :: OS Independent
Requires-Python: >=3
Requires-Dist: ecdsa
Requires-Dist: PyCryptodome
